flask_session/__init__.py
flask_session/sessions.py
Flask_Session-0.4.1.dist-info/LICENSE
Flask_Session-0.4.1.dist-info/METADATA
Flask_Session-0.4.1.dist-info/WHEEL
Flask_Session-0.4.1.dist-info/top_level.txt
Flask_Session-0.4.1.dist-info/RECORD
