Metadata-Version: 2.1
Name: Flask-Session
Version: 0.4.1
Summary: Adds server-side session support to your Flask application
Home-page: https://github.com/fengsp/flask-session
Author: Shipeng Feng
Author-email: fsp261@gmail.com
License: BSD
Platform: any
Classifier: Environment :: Web Environment
Classifier: Intended Audience :: Developers
Classifier: License :: OSI Approved :: BSD License
Classifier: Operating System :: OS Independent
Classifier: Programming Language :: Python :: 2
Classifier: Topic :: Internet :: WWW/HTTP :: Dynamic Content
Classifier: Topic :: Software Development :: Libraries :: Python Modules
License-File: LICENSE
